stellar_stats/__init__.py
stellar_stats/app.py
stellar_stats/auth.py
stellar_stats/cli.py
stellar_stats/config.py
stellar_stats/data.py
stellar_stats/roundtrip.py
stellar_stats/stats.py
stellar_stats/ui.py
stellar_stats/utils.py
stellar_stats/cli/__init__.py
stellar_stats/cli/gen_data_from_cfmmc.py
stellar_stats/cli/gen_data_from_ibflex.py
stellar_stats/cli/gen_investors.py
stellar_stats/cli/gen_rebates.py
stellar_stats/cli/run.py
stellar_stats-0.8.9.dist-info/METADATA
stellar_stats-0.8.9.dist-info/WHEEL
stellar_stats-0.8.9.dist-info/entry_points.txt
stellar_stats-0.8.9.dist-info/top_level.txt
stellar_stats-0.8.9.dist-info/RECORD
