Metadata-Version: 2.4
Name: stellar-stats
Version: 0.8.9
Summary: Stats page for backtest/live trading
Author-email: Keli Hu <dev@keli.hu>
License: MIT
Project-URL: Homepage, https://github.com/keli/stellar-stats
Keywords: trade stats
Requires-Python: >=3.9
Requires-Dist: click
Requires-Dist: tabulate
Requires-Dist: empyrical-reloaded
Requires-Dist: extra-streamlit-components
Requires-Dist: plotly
Requires-Dist: python-dotenv
Requires-Dist: streamlit>=1.39.0
Requires-Dist: tushare
Requires-Dist: yfinance>=0.2.51
